consolekit/__init__.py
consolekit/__init__.pyi
consolekit/_readline.py
consolekit/_readline.pyi
consolekit/_types.py
consolekit/commands.py
consolekit/input.py
consolekit/options.py
consolekit/py.typed
consolekit/terminal_colours.py
consolekit/terminal_colours.pyi
consolekit/testing.py
consolekit/tracebacks.py
consolekit/utils.py
consolekit/versions.py
consolekit-1.12.0.dist-info/licenses/LICENSE
consolekit-1.12.0.dist-info/WHEEL
consolekit-1.12.0.dist-info/METADATA
consolekit-1.12.0.dist-info/RECORD
